aws_kinesis_consumer/__init__.py
aws_kinesis_consumer/__main__.py
aws_kinesis_consumer/aws/__init__.py
aws_kinesis_consumer/aws/aws_services_factory.py
aws_kinesis_consumer/configuration/__init__.py
aws_kinesis_consumer/configuration/configuration.py
aws_kinesis_consumer/configuration/factory.py
aws_kinesis_consumer/error/__init__.py
aws_kinesis_consumer/error/handler.py
aws_kinesis_consumer/kinesis/__init__.py
aws_kinesis_consumer/kinesis/shard.py
aws_kinesis_consumer/kinesis/stream.py
aws_kinesis_consumer/ui/__init__.py
aws_kinesis_consumer/ui/printer.py
aws_kinesis_consumer/ui/progress.py
aws_kinesis_consumer-1.4.1.data/scripts/aws-kinesis-consumer
tasks_helper/__init__.py
tasks_helper/assert_no_todos/__init__.py
tasks_helper/assert_no_todos/assert_no_todos.py
tasks_helper/demo/__init__.py
tasks_helper/demo/demo_consumer.py
tasks_helper/demo/demo_producer.py
tasks_helper/packager/__init__.py
tasks_helper/packager/base.py
tasks_helper/packager/docker.py
tasks_helper/packager/pip.py
tests/__init__.py
tests/configuration/__init__.py
tests/configuration/test_configuration_factory.py
tests/error/__init__.py
tests/error/test_handler.py
tests/kinesis/__init__.py
tests/kinesis/test_shard.py
tests/kinesis/test_stream.py
tests/kinesis/test_stream_concurrently.py
tests/kinesis/dockerized/DockerizedKinesis.py
tests/kinesis/dockerized/__init__.py
tests/ui/__init__.py
tests/ui/test_printer.py
tests/ui/test_progress.py
aws_kinesis_consumer-1.4.1.dist-info/LICENSE
aws_kinesis_consumer-1.4.1.dist-info/METADATA
aws_kinesis_consumer-1.4.1.dist-info/WHEEL
aws_kinesis_consumer-1.4.1.dist-info/top_level.txt
aws_kinesis_consumer-1.4.1.dist-info/RECORD
