Metadata-Version: 2.1
Name: aws-kinesis-consumer
Version: 1.4.1
Summary: Consume an AWS Kinesis Data Stream to look over the records from a terminal
Home-page: https://github.com/thinow/aws-kinesis-consumer
Author: Thierry Nowak
Author-email: thinow@gmail.com
Maintainer: Thierry Nowak
Maintainer-email: thinow@gmail.com
License: MIT
Platform: UNKNOWN
Classifier: Development Status :: 5 - Production/Stable
Classifier: Environment :: Console
Classifier: Intended Audience :: Developers
Classifier: License :: OSI Approved :: MIT License
Classifier: Natural Language :: English
Classifier: Operating System :: OS Independent
Classifier: Programming Language :: Python
Classifier: Programming Language :: Python :: 3
Classifier: Programming Language :: Python :: 3 :: Only
Classifier: Programming Language :: Python :: 3.10
Classifier: Programming Language :: Python :: 3.6
Classifier: Programming Language :: Python :: 3.7
Classifier: Programming Language :: Python :: 3.8
Classifier: Programming Language :: Python :: 3.9
Classifier: Topic :: Scientific/Engineering
Classifier: Topic :: Scientific/Engineering :: Information Analysis
Classifier: Topic :: Utilities
Requires-Python: >=3.6
License-File: LICENSE
Requires-Dist: boto3 (==1.17.34)
Requires-Dist: boto3-type-annotations (==0.3.1)
Requires-Dist: s3transfer (==0.3.7)
Requires-Dist: urllib3 (==1.26.5)
Requires-Dist: jmespath (==0.10.0) ; python_version >= "2.6" and python_version not in "3.0, 3.1, 3.2, 3.3"
Requires-Dist: python-dateutil (==2.8.2) ; python_version >= "2.7" and python_version not in "3.0, 3.1, 3.2, 3.3"
Requires-Dist: six (==1.16.0) ; python_version >= "2.7" and python_version not in "3.0, 3.1, 3.2, 3.3"
Requires-Dist: botocore (==1.20.112) ; python_version >= "2.7" and python_version not in "3.0, 3.1, 3.2, 3.3, 3.4, 3.5"
